{"cameraMode":{"drawMode":0,"name":"Shaded","section":"Shading Mode"},"sceneLighting":true,"audioPlay":false,"sceneViewState":{"showFog":true,"showMaterialUpdate":false,"showSkybox":true,"showFlares":true,"showImageEffects":true,"showParticleSystems":true},"in2DMode":false,"pivot":{"x":3.3445615768432619,"y":0.9384651184082031,"z":2.1475682258605959},"rotation":{"x":-0.004210660234093666,"y":-0.34554603695869448,"z":0.0015890832291916013,"w":-0.9384938478469849},"size":7.006229877471924,"orthographic":false}